my_quickbase/__init__.py
my_quickbase/helpers.py
my_quickbase/quickbase_queries.py
my_quickbase/settings.py
my_quickbase-0.2.1.dist-info/LICENSE
my_quickbase-0.2.1.dist-info/METADATA
my_quickbase-0.2.1.dist-info/WHEEL
my_quickbase-0.2.1.dist-info/top_level.txt
my_quickbase-0.2.1.dist-info/RECORD
