Metadata-Version: 2.1
Name: my-quickbase
Version: 0.2.1
Summary: A lightweight tool for interacting with Quickbase's RESTful API
Home-page: https://github.com/samw1989/my-quickbase
Author: Sam Westrop
Author-email: westrop@meforum.org
License: MIT
Platform: UNKNOWN
License-File: LICENSE
Requires-Dist: pytest
Requires-Dist: requests
Requires-Dist: python-decouple
